[
  {
    "id": 1,
    "nome": "CoordenaĂ§ĂŁo Pindorama",
    "email": "admin@pindorama.local",
    "senha_hash": "$2y$10$I6o6AszNKdfW4wp9nTGmqurCmV9.sLBvzE9fpWZovgXMm6pakdPlu",
    "telefone": "5581995216450",
    "especialidade": "CoordenaĂ§ĂŁo do EspaĂ§o",
    "ativo": true,
    "papel": "admin",
    "criado_em": "2026-05-27T00:00:00-03:00"
  },
  {
    "id": 2,
    "nome": "Terapeuta Exemplo",
    "email": "terapeuta@pindorama.local",
    "senha_hash": "$2y$10$8/bu2eN4T1wSouAP.UrKQ.bWSZxL7I6Huqr1kl3aHZAwwNcyP3pRe",
    "telefone": "5581900000000",
    "especialidade": "Massoterapia",
    "ativo": true,
    "papel": "terapeuta",
    "criado_em": "2026-05-27T00:00:00-03:00"
  },
  {
    "id": 3,
    "nome": "P. Koilthy",
    "email": "p.koilthy@gmail.com",
    "senha_hash": "$2y$10$TdAm3FU72srMEaTLrN.M3upMMU/WOHuDaS.ERGntjm346k2w9W9cS",
    "telefone": "",
    "especialidade": "Terapeuta",
    "ativo": true,
    "papel": "terapeuta",
    "criado_em": "2026-05-27T00:00:00-03:00"
  },
  {
    "id": 4,
    "nome": "Luiz Mario Barros Moutinho",
    "email": "luizmariomoutinho1@gmail.com",
    "senha_hash": "$2y$10$ppAz5LbW5blSb2EV4e3icesSmOBY7ODKEVC2WgrF/ZQTxmwA.pmF.",
    "telefone": "",
    "especialidade": "Terapeuta",
    "ativo": true,
    "papel": "terapeuta",
    "must_change_password": true,
    "criado_em": "2026-06-02T00:00:00-03:00"
  }
]
